jovyan/__init__.py
jovyan/__version__.py
jovyan/tests/__init__.py
jovyan/tests/conftest.py
jovyan/tests/test_client.py
jovyan-0.1.0.dist-info/METADATA
jovyan-0.1.0.dist-info/WHEEL
jovyan-0.1.0.dist-info/licenses/LICENSE
jovyan-0.1.0.dist-info/RECORD
